{
    "configurations": [
        {
            "name": "Win32",
            "includePath": [
                "${workspaceFolder}/**"
            ],
            "defines": [
                "_DEBUG",
                "UNICODE",
                "_UNICODE"
            ],
            "cStandard": "c17",
            "cppStandard": "c++17",
            "intelliSenseMode": "windows-msvc-x64",
            "compilerPath": "d:\\CodingSoft\\Espressif\\frameworks\\esp-idf-v5.0.2\\tools\\tools\\xtensa-esp32-elf\\esp-2022r1-11.2.0\\xtensa-esp32-elf\\bin\\xtensa-esp32-elf-gcc.exe",
            "compileCommands": "${workspaceFolder}/build/compile_commands.json"
        }
    ],
    "version": 4
}